cs/threads.py
cs_threads-20250528.dist-info/WHEEL
cs_threads-20250528.dist-info/METADATA
cs_threads-20250528.dist-info/RECORD
